mcp_fmu/__init__.py
mcp_fmu/cli.py
mcp_fmu/server.py
mcp_fmu-0.1.2.dist-info/METADATA
mcp_fmu-0.1.2.dist-info/WHEEL
mcp_fmu-0.1.2.dist-info/entry_points.txt
mcp_fmu-0.1.2.dist-info/top_level.txt
mcp_fmu-0.1.2.dist-info/RECORD
