Metadata-Version: 2.4
Name: mcp-fmu
Version: 0.1.2
Summary: mcp server for fmu simulation
Requires-Python: >=3.11
Requires-Dist: fastmcp>=2.3.4
Requires-Dist: fmpy>=0.3.23
Requires-Dist: pandas>=2.2.3
